{"student_id":"S4742","name":"Omar Johnson","department":"Mathematics","gender":"Male","age":24,"attendance":71.09,"midterm":86.12,"assignments_avg":83.98,"quizzes_avg":52.13,"participation":87.4,"projects":62.22,"grade":"D","risk_score":0.3337,"risk_band":"LOW","email":"student3742@university.com","first_name":"Omar","last_name":"Johnson","study_hours":11.5,"stress":2,"sleep":4.7,"extracurricular":"Yes","internet_access":"Yes","parent_education":"Unknown","family_income":"High","final_score":46.71,"total_score":65.4415,"graph_engagement":1.0,"anomaly":{"start_day":10,"end_day":16,"mean_attended":0.286,"std_attended":0.452,"reason":"attendance dropped below 50%; high variance (erratic)"},"daily_logs":[{"day":1,"attended":0,"resource_hits":3},{"day":2,"attended":1,"resource_hits":2},{"day":3,"attended":0,"resource_hits":1},{"day":4,"attended":1,"resource_hits":0},{"day":5,"attended":1,"resource_hits":5},{"day":6,"attended":0,"resource_hits":2},{"day":7,"attended":1,"resource_hits":1},{"day":8,"attended":0,"resource_hits":4},{"day":9,"attended":1,"resource_hits":0},{"day":10,"attended":0,"resource_hits":3},{"day":11,"attended":1,"resource_hits":3},{"day":12,"attended":0,"resource_hits":2},{"day":13,"attended":0,"resource_hits":2},{"day":14,"attended":1,"resource_hits":3},{"day":15,"attended":0,"resource_hits":2},{"day":16,"attended":0,"resource_hits":2},{"day":17,"attended":1,"resource_hits":3},{"day":18,"attended":1,"resource_hits":0},{"day":19,"attended":1,"resource_hits":4},{"day":20,"attended":1,"resource_hits":1},{"day":21,"attended":1,"resource_hits":1},{"day":22,"attended":0,"resource_hits":0},{"day":23,"attended":0,"resource_hits":1},{"day":24,"attended":1,"resource_hits":3},{"day":25,"attended":0,"resource_hits":0},{"day":26,"attended":1,"resource_hits":2},{"day":27,"attended":1,"resource_hits":1},{"day":28,"attended":1,"resource_hits":1},{"day":29,"attended":1,"resource_hits":0},{"day":30,"attended":1,"resource_hits":1},{"day":31,"attended":1,"resource_hits":2},{"day":32,"attended":1,"resource_hits":2},{"day":33,"attended":1,"resource_hits":3},{"day":34,"attended":1,"resource_hits":3},{"day":35,"attended":1,"resource_hits":0},{"day":36,"attended":1,"resource_hits":2},{"day":37,"attended":1,"resource_hits":3},{"day":38,"attended":1,"resource_hits":0},{"day":39,"attended":1,"resource_hits":0},{"day":40,"attended":1,"resource_hits":0},{"day":41,"attended":0,"resource_hits":0},{"day":42,"attended":1,"resource_hits":3},{"day":43,"attended":1,"resource_hits":0},{"day":44,"attended":1,"resource_hits":0},{"day":45,"attended":1,"resource_hits":1},{"day":46,"attended":1,"resource_hits":1},{"day":47,"attended":1,"resource_hits":1},{"day":48,"attended":1,"resource_hits":1},{"day":49,"attended":1,"resource_hits":2},{"day":50,"attended":0,"resource_hits":1},{"day":51,"attended":1,"resource_hits":2},{"day":52,"attended":0,"resource_hits":0},{"day":53,"attended":1,"resource_hits":2},{"day":54,"attended":1,"resource_hits":1},{"day":55,"attended":0,"resource_hits":1},{"day":56,"attended":1,"resource_hits":4},{"day":57,"attended":0,"resource_hits":1},{"day":58,"attended":1,"resource_hits":4},{"day":59,"attended":0,"resource_hits":4},{"day":60,"attended":1,"resource_hits":2},{"day":61,"attended":0,"resource_hits":2},{"day":62,"attended":1,"resource_hits":2},{"day":63,"attended":0,"resource_hits":1},{"day":64,"attended":1,"resource_hits":2},{"day":65,"attended":1,"resource_hits":1},{"day":66,"attended":1,"resource_hits":0},{"day":67,"attended":1,"resource_hits":2},{"day":68,"attended":1,"resource_hits":0},{"day":69,"attended":1,"resource_hits":1},{"day":70,"attended":1,"resource_hits":1},{"day":71,"attended":0,"resource_hits":1},{"day":72,"attended":1,"resource_hits":3},{"day":73,"attended":1,"resource_hits":2},{"day":74,"attended":1,"resource_hits":0},{"day":75,"attended":0,"resource_hits":2},{"day":76,"attended":1,"resource_hits":0},{"day":77,"attended":0,"resource_hits":2},{"day":78,"attended":1,"resource_hits":2},{"day":79,"attended":1,"resource_hits":1},{"day":80,"attended":1,"resource_hits":1},{"day":81,"attended":0,"resource_hits":2},{"day":82,"attended":1,"resource_hits":2},{"day":83,"attended":1,"resource_hits":1},{"day":84,"attended":1,"resource_hits":3}]}